teflo_openstack_client_plugin/__init__.py
teflo_openstack_client_plugin/os_client_provisioner.py
teflo_openstack_client_plugin/files/osp_schema_extensions.py
teflo_openstack_client_plugin/files/schema.yml
teflo_openstack_client_plugin/helpers/__init__.py
teflo_openstack_client_plugin/helpers/os_client_helper.py
teflo_openstack_client_plugin-1.0.2.dist-info/AUTHORS
teflo_openstack_client_plugin-1.0.2.dist-info/LICENSE
teflo_openstack_client_plugin-1.0.2.dist-info/METADATA
teflo_openstack_client_plugin-1.0.2.dist-info/WHEEL
teflo_openstack_client_plugin-1.0.2.dist-info/entry_points.txt
teflo_openstack_client_plugin-1.0.2.dist-info/top_level.txt
teflo_openstack_client_plugin-1.0.2.dist-info/RECORD
