Metadata-Version: 2.1
Name: teflo-openstack-client-plugin
Version: 1.0.2
Summary: openstack client provisioner plugin for Teflo
Author: Red Hat Inc
Classifier: Development Status :: 2 - Pre-Alpha
Classifier: Intended Audience :: Developers
Classifier: Natural Language :: English
Classifier: License :: OSI Approved :: GNU Lesser General Public License v3 (LGPLv3)
Classifier: Programming Language :: Python
Classifier: Programming Language :: Python :: 3.6
License-File: LICENSE
License-File: AUTHORS
Requires-Dist: python-openstackclient (<=5.5.0)
Requires-Dist: ospclientsdk
